{
  "type": "File",
  "start": 0,
  "end": 552,
  "loc": {
    "start": {
      "line": 1,
      "column": 0
    },
    "end": {
      "line": 25,
      "column": 0
    }
  },
  "program": {
    "type": "Program",
    "start": 0,
    "end": 552,
    "loc": {
      "start": {
        "line": 1,
        "column": 0
      },
      "end": {
        "line": 25,
        "column": 0
      }
    },
    "sourceType": "module",
    "body": [
      {
        "type": "ImportDeclaration",
        "start": 0,
        "end": 37,
        "loc": {
          "start": {
            "line": 1,
            "column": 0
          },
          "end": {
            "line": 1,
            "column": 37
          }
        },
        "specifiers": [
          {
            "type": "ImportSpecifier",
            "start": 9,
            "end": 16,
            "loc": {
              "start": {
                "line": 1,
                "column": 9
              },
              "end": {
                "line": 1,
                "column": 16
              }
            },
            "imported": {
              "type": "Identifier",
              "start": 9,
              "end": 16,
              "loc": {
                "start": {
                  "line": 1,
                  "column": 9
                },
                "end": {
                  "line": 1,
                  "column": 16
                },
                "identifierName": "connect"
              },
              "name": "connect"
            },
            "local": {
              "type": "Identifier",
              "start": 9,
              "end": 16,
              "loc": {
                "start": {
                  "line": 1,
                  "column": 9
                },
                "end": {
                  "line": 1,
                  "column": 16
                },
                "identifierName": "connect"
              },
              "name": "connect"
            }
          }
        ],
        "source": {
          "type": "StringLiteral",
          "start": 24,
          "end": 37,
          "loc": {
            "start": {
              "line": 1,
              "column": 24
            },
            "end": {
              "line": 1,
              "column": 37
            }
          },
          "extra": {
            "rawValue": "react-redux",
            "raw": "'react-redux'"
          },
          "value": "react-redux"
        }
      },
      {
        "type": "ImportDeclaration",
        "start": 38,
        "end": 99,
        "loc": {
          "start": {
            "line": 2,
            "column": 0
          },
          "end": {
            "line": 2,
            "column": 61
          }
        },
        "specifiers": [
          {
            "type": "ImportSpecifier",
            "start": 47,
            "end": 66,
            "loc": {
              "start": {
                "line": 2,
                "column": 9
              },
              "end": {
                "line": 2,
                "column": 28
              }
            },
            "imported": {
              "type": "Identifier",
              "start": 47,
              "end": 66,
              "loc": {
                "start": {
                  "line": 2,
                  "column": 9
                },
                "end": {
                  "line": 2,
                  "column": 28
                },
                "identifierName": "changeOperationMode"
              },
              "name": "changeOperationMode"
            },
            "local": {
              "type": "Identifier",
              "start": 47,
              "end": 66,
              "loc": {
                "start": {
                  "line": 2,
                  "column": 9
                },
                "end": {
                  "line": 2,
                  "column": 28
                },
                "identifierName": "changeOperationMode"
              },
              "name": "changeOperationMode"
            }
          }
        ],
        "source": {
          "type": "StringLiteral",
          "start": 74,
          "end": 99,
          "loc": {
            "start": {
              "line": 2,
              "column": 36
            },
            "end": {
              "line": 2,
              "column": 61
            }
          },
          "extra": {
            "rawValue": "../actions/OrderActions",
            "raw": "'../actions/OrderActions'"
          },
          "value": "../actions/OrderActions"
        }
      },
      {
        "type": "ImportDeclaration",
        "start": 100,
        "end": 149,
        "loc": {
          "start": {
            "line": 3,
            "column": 0
          },
          "end": {
            "line": 3,
            "column": 49
          }
        },
        "specifiers": [
          {
            "type": "ImportSpecifier",
            "start": 109,
            "end": 119,
            "loc": {
              "start": {
                "line": 3,
                "column": 9
              },
              "end": {
                "line": 3,
                "column": 19
              }
            },
            "imported": {
              "type": "Identifier",
              "start": 109,
              "end": 119,
              "loc": {
                "start": {
                  "line": 3,
                  "column": 9
                },
                "end": {
                  "line": 3,
                  "column": 19
                },
                "identifierName": "uiHideMenu"
              },
              "name": "uiHideMenu"
            },
            "local": {
              "type": "Identifier",
              "start": 109,
              "end": 119,
              "loc": {
                "start": {
                  "line": 3,
                  "column": 9
                },
                "end": {
                  "line": 3,
                  "column": 19
                },
                "identifierName": "uiHideMenu"
              },
              "name": "uiHideMenu"
            }
          }
        ],
        "source": {
          "type": "StringLiteral",
          "start": 127,
          "end": 149,
          "loc": {
            "start": {
              "line": 3,
              "column": 27
            },
            "end": {
              "line": 3,
              "column": 49
            }
          },
          "extra": {
            "rawValue": "../actions/UIActions",
            "raw": "'../actions/UIActions'"
          },
          "value": "../actions/UIActions"
        }
      },
      {
        "type": "ImportDeclaration",
        "start": 150,
        "end": 207,
        "loc": {
          "start": {
            "line": 4,
            "column": 0
          },
          "end": {
            "line": 4,
            "column": 57
          }
        },
        "specifiers": [
          {
            "type": "ImportDefaultSpecifier",
            "start": 157,
            "end": 169,
            "loc": {
              "start": {
                "line": 4,
                "column": 7
              },
              "end": {
                "line": 4,
                "column": 19
              }
            },
            "local": {
              "type": "Identifier",
              "start": 157,
              "end": 169,
              "loc": {
                "start": {
                  "line": 4,
                  "column": 7
                },
                "end": {
                  "line": 4,
                  "column": 19
                },
                "identifierName": "ModeSwitcher"
              },
              "name": "ModeSwitcher"
            }
          }
        ],
        "source": {
          "type": "StringLiteral",
          "start": 175,
          "end": 207,
          "loc": {
            "start": {
              "line": 4,
              "column": 25
            },
            "end": {
              "line": 4,
              "column": 57
            }
          },
          "extra": {
            "rawValue": "../components/ModeSwitcher.jsx",
            "raw": "'../components/ModeSwitcher.jsx'"
          },
          "value": "../components/ModeSwitcher.jsx"
        }
      },
      {
        "type": "VariableDeclaration",
        "start": 209,
        "end": 257,
        "loc": {
          "start": {
            "line": 6,
            "column": 0
          },
          "end": {
            "line": 8,
            "column": 1
          }
        },
        "declarations": [
          {
            "type": "VariableDeclarator",
            "start": 215,
            "end": 257,
            "loc": {
              "start": {
                "line": 6,
                "column": 6
              },
              "end": {
                "line": 8,
                "column": 1
              }
            },
            "id": {
              "type": "Identifier",
              "start": 215,
              "end": 230,
              "loc": {
                "start": {
                  "line": 6,
                  "column": 6
                },
                "end": {
                  "line": 6,
                  "column": 21
                },
                "identifierName": "mapStateToProps"
              },
              "name": "mapStateToProps"
            },
            "init": {
              "type": "ArrowFunctionExpression",
              "start": 233,
              "end": 257,
              "loc": {
                "start": {
                  "line": 6,
                  "column": 24
                },
                "end": {
                  "line": 8,
                  "column": 1
                }
              },
              "id": {
                "type": "Identifier",
                "start": 215,
                "end": 230,
                "loc": {
                  "start": {
                    "line": 6,
                    "column": 6
                  },
                  "end": {
                    "line": 6,
                    "column": 21
                  },
                  "identifierName": "mapStateToProps"
                },
                "name": "mapStateToProps"
              },
              "generator": false,
              "expression": false,
              "async": false,
              "params": [
                {
                  "type": "Identifier",
                  "start": 233,
                  "end": 238,
                  "loc": {
                    "start": {
                      "line": 6,
                      "column": 24
                    },
                    "end": {
                      "line": 6,
                      "column": 29
                    },
                    "identifierName": "state"
                  },
                  "name": "state"
                }
              ],
              "body": {
                "type": "BlockStatement",
                "start": 242,
                "end": 257,
                "loc": {
                  "start": {
                    "line": 6,
                    "column": 33
                  },
                  "end": {
                    "line": 8,
                    "column": 1
                  }
                },
                "body": [
                  {
                    "type": "ReturnStatement",
                    "start": 246,
                    "end": 255,
                    "loc": {
                      "start": {
                        "line": 7,
                        "column": 2
                      },
                      "end": {
                        "line": 7,
                        "column": 11
                      }
                    },
                    "argument": {
                      "type": "ObjectExpression",
                      "start": 253,
                      "end": 255,
                      "loc": {
                        "start": {
                          "line": 7,
                          "column": 9
                        },
                        "end": {
                          "line": 7,
                          "column": 11
                        }
                      },
                      "properties": []
                    }
                  }
                ],
                "directives": []
              }
            }
          }
        ],
        "kind": "const"
      },
      {
        "type": "VariableDeclaration",
        "start": 259,
        "end": 417,
        "loc": {
          "start": {
            "line": 10,
            "column": 0
          },
          "end": {
            "line": 17,
            "column": 1
          }
        },
        "declarations": [
          {
            "type": "VariableDeclarator",
            "start": 265,
            "end": 417,
            "loc": {
              "start": {
                "line": 10,
                "column": 6
              },
              "end": {
                "line": 17,
                "column": 1
              }
            },
            "id": {
              "type": "Identifier",
              "start": 265,
              "end": 283,
              "loc": {
                "start": {
                  "line": 10,
                  "column": 6
                },
                "end": {
                  "line": 10,
                  "column": 24
                },
                "identifierName": "mapDispatchToProps"
              },
              "name": "mapDispatchToProps"
            },
            "init": {
              "type": "ArrowFunctionExpression",
              "start": 286,
              "end": 417,
              "loc": {
                "start": {
                  "line": 10,
                  "column": 27
                },
                "end": {
                  "line": 17,
                  "column": 1
                }
              },
              "id": {
                "type": "Identifier",
                "start": 265,
                "end": 283,
                "loc": {
                  "start": {
                    "line": 10,
                    "column": 6
                  },
                  "end": {
                    "line": 10,
                    "column": 24
                  },
                  "identifierName": "mapDispatchToProps"
                },
                "name": "mapDispatchToProps"
              },
              "generator": false,
              "expression": false,
              "async": false,
              "params": [
                {
                  "type": "Identifier",
                  "start": 286,
                  "end": 294,
                  "loc": {
                    "start": {
                      "line": 10,
                      "column": 27
                    },
                    "end": {
                      "line": 10,
                      "column": 35
                    },
                    "identifierName": "dispatch"
                  },
                  "name": "dispatch"
                }
              ],
              "body": {
                "type": "BlockStatement",
                "start": 298,
                "end": 417,
                "loc": {
                  "start": {
                    "line": 10,
                    "column": 39
                  },
                  "end": {
                    "line": 17,
                    "column": 1
                  }
                },
                "body": [
                  {
                    "type": "ReturnStatement",
                    "start": 302,
                    "end": 415,
                    "loc": {
                      "start": {
                        "line": 11,
                        "column": 2
                      },
                      "end": {
                        "line": 16,
                        "column": 3
                      }
                    },
                    "argument": {
                      "type": "ObjectExpression",
                      "start": 309,
                      "end": 415,
                      "loc": {
                        "start": {
                          "line": 11,
                          "column": 9
                        },
                        "end": {
                          "line": 16,
                          "column": 3
                        }
                      },
                      "properties": [
                        {
                          "type": "ObjectProperty",
                          "start": 315,
                          "end": 411,
                          "loc": {
                            "start": {
                              "line": 12,
                              "column": 4
                            },
                            "end": {
                              "line": 15,
                              "column": 5
                            }
                          },
                          "method": false,
                          "shorthand": false,
                          "computed": false,
                          "key": {
                            "type": "Identifier",
                            "start": 315,
                            "end": 323,
                            "loc": {
                              "start": {
                                "line": 12,
                                "column": 4
                              },
                              "end": {
                                "line": 12,
                                "column": 12
                              },
                              "identifierName": "onSwitch"
                            },
                            "name": "onSwitch"
                          },
                          "value": {
                            "type": "ArrowFunctionExpression",
                            "start": 325,
                            "end": 411,
                            "loc": {
                              "start": {
                                "line": 12,
                                "column": 14
                              },
                              "end": {
                                "line": 15,
                                "column": 5
                              }
                            },
                            "id": null,
                            "generator": false,
                            "expression": false,
                            "async": false,
                            "params": [
                              {
                                "type": "Identifier",
                                "start": 325,
                                "end": 329,
                                "loc": {
                                  "start": {
                                    "line": 12,
                                    "column": 14
                                  },
                                  "end": {
                                    "line": 12,
                                    "column": 18
                                  },
                                  "identifierName": "mode"
                                },
                                "name": "mode"
                              }
                            ],
                            "body": {
                              "type": "BlockStatement",
                              "start": 333,
                              "end": 411,
                              "loc": {
                                "start": {
                                  "line": 12,
                                  "column": 22
                                },
                                "end": {
                                  "line": 15,
                                  "column": 5
                                }
                              },
                              "body": [
                                {
                                  "type": "ExpressionStatement",
                                  "start": 341,
                                  "end": 376,
                                  "loc": {
                                    "start": {
                                      "line": 13,
                                      "column": 6
                                    },
                                    "end": {
                                      "line": 13,
                                      "column": 41
                                    }
                                  },
                                  "expression": {
                                    "type": "CallExpression",
                                    "start": 341,
                                    "end": 376,
                                    "loc": {
                                      "start": {
                                        "line": 13,
                                        "column": 6
                                      },
                                      "end": {
                                        "line": 13,
                                        "column": 41
                                      }
                                    },
                                    "callee": {
                                      "type": "Identifier",
                                      "start": 341,
                                      "end": 349,
                                      "loc": {
                                        "start": {
                                          "line": 13,
                                          "column": 6
                                        },
                                        "end": {
                                          "line": 13,
                                          "column": 14
                                        },
                                        "identifierName": "dispatch"
                                      },
                                      "name": "dispatch"
                                    },
                                    "arguments": [
                                      {
                                        "type": "CallExpression",
                                        "start": 350,
                                        "end": 375,
                                        "loc": {
                                          "start": {
                                            "line": 13,
                                            "column": 15
                                          },
                                          "end": {
                                            "line": 13,
                                            "column": 40
                                          }
                                        },
                                        "callee": {
                                          "type": "Identifier",
                                          "start": 350,
                                          "end": 369,
                                          "loc": {
                                            "start": {
                                              "line": 13,
                                              "column": 15
                                            },
                                            "end": {
                                              "line": 13,
                                              "column": 34
                                            },
                                            "identifierName": "changeOperationMode"
                                          },
                                          "name": "changeOperationMode"
                                        },
                                        "arguments": [
                                          {
                                            "type": "Identifier",
                                            "start": 370,
                                            "end": 374,
                                            "loc": {
                                              "start": {
                                                "line": 13,
                                                "column": 35
                                              },
                                              "end": {
                                                "line": 13,
                                                "column": 39
                                              },
                                              "identifierName": "mode"
                                            },
                                            "name": "mode"
                                          }
                                        ]
                                      }
                                    ]
                                  }
                                },
                                {
                                  "type": "ExpressionStatement",
                                  "start": 383,
                                  "end": 405,
                                  "loc": {
                                    "start": {
                                      "line": 14,
                                      "column": 6
                                    },
                                    "end": {
                                      "line": 14,
                                      "column": 28
                                    }
                                  },
                                  "expression": {
                                    "type": "CallExpression",
                                    "start": 383,
                                    "end": 405,
                                    "loc": {
                                      "start": {
                                        "line": 14,
                                        "column": 6
                                      },
                                      "end": {
                                        "line": 14,
                                        "column": 28
                                      }
                                    },
                                    "callee": {
                                      "type": "Identifier",
                                      "start": 383,
                                      "end": 391,
                                      "loc": {
                                        "start": {
                                          "line": 14,
                                          "column": 6
                                        },
                                        "end": {
                                          "line": 14,
                                          "column": 14
                                        },
                                        "identifierName": "dispatch"
                                      },
                                      "name": "dispatch"
                                    },
                                    "arguments": [
                                      {
                                        "type": "CallExpression",
                                        "start": 392,
                                        "end": 404,
                                        "loc": {
                                          "start": {
                                            "line": 14,
                                            "column": 15
                                          },
                                          "end": {
                                            "line": 14,
                                            "column": 27
                                          }
                                        },
                                        "callee": {
                                          "type": "Identifier",
                                          "start": 392,
                                          "end": 402,
                                          "loc": {
                                            "start": {
                                              "line": 14,
                                              "column": 15
                                            },
                                            "end": {
                                              "line": 14,
                                              "column": 25
                                            },
                                            "identifierName": "uiHideMenu"
                                          },
                                          "name": "uiHideMenu"
                                        },
                                        "arguments": []
                                      }
                                    ]
                                  }
                                }
                              ],
                              "directives": []
                            }
                          }
                        }
                      ]
                    }
                  }
                ],
                "directives": []
              }
            }
          }
        ],
        "kind": "const"
      },
      {
        "type": "Identifier",
        "start": 419,
        "end": 513,
        "loc": {
          "start": {
            "line": 19,
            "column": 0
          },
          "end": {
            "line": 22,
            "column": 15
          }
        },
        "declarations": [
          {
            "type": "VariableDeclarator",
            "start": 425,
            "end": 513,
            "loc": {
              "start": {
                "line": 19,
                "column": 6
              },
              "end": {
                "line": 22,
                "column": 15
              }
            },
            "id": {
              "type": "Identifier",
              "start": 425,
              "end": 446,
              "loc": {
                "start": {
                  "line": 19,
                  "column": 6
                },
                "end": {
                  "line": 19,
                  "column": 27
                },
                "identifierName": "ModeSwitcherContainer"
              },
              "name": "ModeSwitcherContainer"
            },
            "init": {
              "type": "CallExpression",
              "start": 449,
              "end": 513,
              "loc": {
                "start": {
                  "line": 19,
                  "column": 30
                },
                "end": {
                  "line": 22,
                  "column": 15
                }
              },
              "callee": {
                "type": "CallExpression",
                "start": 449,
                "end": 499,
                "loc": {
                  "start": {
                    "line": 19,
                    "column": 30
                  },
                  "end": {
                    "line": 22,
                    "column": 1
                  }
                },
                "callee": {
                  "type": "Identifier",
                  "start": 449,
                  "end": 456,
                  "loc": {
                    "start": {
                      "line": 19,
                      "column": 30
                    },
                    "end": {
                      "line": 19,
                      "column": 37
                    },
                    "identifierName": "connect"
                  },
                  "name": "connect"
                },
                "arguments": [
                  {
                    "type": "Identifier",
                    "start": 460,
                    "end": 475,
                    "loc": {
                      "start": {
                        "line": 20,
                        "column": 2
                      },
                      "end": {
                        "line": 20,
                        "column": 17
                      },
                      "identifierName": "mapStateToProps"
                    },
                    "name": "mapStateToProps"
                  },
                  {
                    "type": "Identifier",
                    "start": 479,
                    "end": 497,
                    "loc": {
                      "start": {
                        "line": 21,
                        "column": 2
                      },
                      "end": {
                        "line": 21,
                        "column": 20
                      },
                      "identifierName": "mapDispatchToProps"
                    },
                    "name": "mapDispatchToProps"
                  }
                ]
              },
              "arguments": [
                {
                  "type": "Identifier",
                  "start": 500,
                  "end": 512,
                  "loc": {
                    "start": {
                      "line": 22,
                      "column": 2
                    },
                    "end": {
                      "line": 22,
                      "column": 14
                    },
                    "identifierName": "ModeSwitcher"
                  },
                  "name": "ModeSwitcher"
                }
              ]
            }
          }
        ],
        "kind": "const",
        "name": "_",
        "leadingComments": [],
        "trailingComments": []
      },
      {
        "type": "Identifier",
        "start": 515,
        "end": 551,
        "loc": {
          "start": {
            "line": 24,
            "column": 0
          },
          "end": {
            "line": 24,
            "column": 36
          }
        },
        "declaration": {
          "type": "Identifier",
          "start": 530,
          "end": 551,
          "loc": {
            "start": {
              "line": 24,
              "column": 15
            },
            "end": {
              "line": 24,
              "column": 36
            },
            "identifierName": "ModeSwitcherContainer"
          },
          "name": "ModeSwitcherContainer"
        },
        "name": "_",
        "leadingComments": [],
        "trailingComments": []
      },
      {
        "type": "ExportDefaultDeclaration",
        "start": 515,
        "end": 551,
        "loc": {
          "start": {
            "line": 24,
            "column": 0
          },
          "end": {
            "line": 24,
            "column": 36
          }
        },
        "declaration": {
          "type": "VariableDeclaration",
          "start": 419,
          "end": 513,
          "loc": {
            "start": {
              "line": 19,
              "column": 0
            },
            "end": {
              "line": 22,
              "column": 15
            }
          },
          "declarations": [
            {
              "type": "VariableDeclarator",
              "start": 425,
              "end": 513,
              "loc": {
                "start": {
                  "line": 19,
                  "column": 6
                },
                "end": {
                  "line": 22,
                  "column": 15
                }
              },
              "id": {
                "type": "Identifier",
                "start": 425,
                "end": 446,
                "loc": {
                  "start": {
                    "line": 19,
                    "column": 6
                  },
                  "end": {
                    "line": 19,
                    "column": 27
                  },
                  "identifierName": "ModeSwitcherContainer"
                },
                "name": "ModeSwitcherContainer"
              },
              "init": {
                "type": "CallExpression",
                "start": 449,
                "end": 513,
                "loc": {
                  "start": {
                    "line": 19,
                    "column": 30
                  },
                  "end": {
                    "line": 22,
                    "column": 15
                  }
                },
                "callee": {
                  "type": "CallExpression",
                  "start": 449,
                  "end": 499,
                  "loc": {
                    "start": {
                      "line": 19,
                      "column": 30
                    },
                    "end": {
                      "line": 22,
                      "column": 1
                    }
                  },
                  "callee": {
                    "type": "Identifier",
                    "start": 449,
                    "end": 456,
                    "loc": {
                      "start": {
                        "line": 19,
                        "column": 30
                      },
                      "end": {
                        "line": 19,
                        "column": 37
                      },
                      "identifierName": "connect"
                    },
                    "name": "connect"
                  },
                  "arguments": [
                    {
                      "type": "Identifier",
                      "start": 460,
                      "end": 475,
                      "loc": {
                        "start": {
                          "line": 20,
                          "column": 2
                        },
                        "end": {
                          "line": 20,
                          "column": 17
                        },
                        "identifierName": "mapStateToProps"
                      },
                      "name": "mapStateToProps"
                    },
                    {
                      "type": "Identifier",
                      "start": 479,
                      "end": 497,
                      "loc": {
                        "start": {
                          "line": 21,
                          "column": 2
                        },
                        "end": {
                          "line": 21,
                          "column": 20
                        },
                        "identifierName": "mapDispatchToProps"
                      },
                      "name": "mapDispatchToProps"
                    }
                  ]
                },
                "arguments": [
                  {
                    "type": "Identifier",
                    "start": 500,
                    "end": 512,
                    "loc": {
                      "start": {
                        "line": 22,
                        "column": 2
                      },
                      "end": {
                        "line": 22,
                        "column": 14
                      },
                      "identifierName": "ModeSwitcher"
                    },
                    "name": "ModeSwitcher"
                  }
                ]
              }
            }
          ],
          "kind": "const",
          "leadingComments": [],
          "trailingComments": []
        }
      }
    ],
    "directives": []
  },
  "comments": [],
  "tokens": [
    {
      "type": {
        "label": "import",
        "keyword": "import",
        "beforeExpr": false,
        "startsExpr": false,
        "rightAssociative": false,
        "isLoop": false,
        "isAssign": false,
        "prefix": false,
        "postfix": false,
        "binop": null,
        "updateContext": null
      },
      "value": "import",
      "start": 0,
      "end": 6,
      "loc": {
        "start": {
          "line": 1,
          "column": 0
        },
        "end": {
          "line": 1,
          "column": 6
        }
      }
    },
    {
      "type": {
        "label": "{",
        "beforeExpr": true,
        "startsExpr": true,
        "rightAssociative": false,
        "isLoop": false,
        "isAssign": false,
        "prefix": false,
        "postfix": false,
        "binop": null
      },
      "start": 7,
      "end": 8,
      "loc": {
        "start": {
          "line": 1,
          "column": 7
        },
        "end": {
          "line": 1,
          "column": 8
        }
      }
    },
    {
      "type": {
        "label": "name",
        "beforeExpr": false,
        "startsExpr": true,
        "rightAssociative": false,
        "isLoop": false,
        "isAssign": false,
        "prefix": false,
        "postfix": false,
        "binop": null
      },
      "value": "connect",
      "start": 9,
      "end": 16,
      "loc": {
        "start": {
          "line": 1,
          "column": 9
        },
        "end": {
          "line": 1,
          "column": 16
        }
      }
    },
    {
      "type": {
        "label": "}",
        "beforeExpr": false,
        "startsExpr": false,
        "rightAssociative": false,
        "isLoop": false,
        "isAssign": false,
        "prefix": false,
        "postfix": false,
        "binop": null
      },
      "start": 17,
      "end": 18,
      "loc": {
        "start": {
          "line": 1,
          "column": 17
        },
        "end": {
          "line": 1,
          "column": 18
        }
      }
    },
    {
      "type": {
        "label": "name",
        "beforeExpr": false,
        "startsExpr": true,
        "rightAssociative": false,
        "isLoop": false,
        "isAssign": false,
        "prefix": false,
        "postfix": false,
        "binop": null
      },
      "value": "from",
      "start": 19,
      "end": 23,
      "loc": {
        "start": {
          "line": 1,
          "column": 19
        },
        "end": {
          "line": 1,
          "column": 23
        }
      }
    },
    {
      "type": {
        "label": "string",
        "beforeExpr": false,
        "startsExpr": true,
        "rightAssociative": false,
        "isLoop": false,
        "isAssign": false,
        "prefix": false,
        "postfix": false,
        "binop": null,
        "updateContext": null
      },
      "value": "react-redux",
      "start": 24,
      "end": 37,
      "loc": {
        "start": {
          "line": 1,
          "column": 24
        },
        "end": {
          "line": 1,
          "column": 37
        }
      }
    },
    {
      "type": {
        "label": "import",
        "keyword": "import",
        "beforeExpr": false,
        "startsExpr": false,
        "rightAssociative": false,
        "isLoop": false,
        "isAssign": false,
        "prefix": false,
        "postfix": false,
        "binop": null,
        "updateContext": null
      },
      "value": "import",
      "start": 38,
      "end": 44,
      "loc": {
        "start": {
          "line": 2,
          "column": 0
        },
        "end": {
          "line": 2,
          "column": 6
        }
      }
    },
    {
      "type": {
        "label": "{",
        "beforeExpr": true,
        "startsExpr": true,
        "rightAssociative": false,
        "isLoop": false,
        "isAssign": false,
        "prefix": false,
        "postfix": false,
        "binop": null
      },
      "start": 45,
      "end": 46,
      "loc": {
        "start": {
          "line": 2,
          "column": 7
        },
        "end": {
          "line": 2,
          "column": 8
        }
      }
    },
    {
      "type": {
        "label": "name",
        "beforeExpr": false,
        "startsExpr": true,
        "rightAssociative": false,
        "isLoop": false,
        "isAssign": false,
        "prefix": false,
        "postfix": false,
        "binop": null
      },
      "value": "changeOperationMode",
      "start": 47,
      "end": 66,
      "loc": {
        "start": {
          "line": 2,
          "column": 9
        },
        "end": {
          "line": 2,
          "column": 28
        }
      }
    },
    {
      "type": {
        "label": "}",
        "beforeExpr": false,
        "startsExpr": false,
        "rightAssociative": false,
        "isLoop": false,
        "isAssign": false,
        "prefix": false,
        "postfix": false,
        "binop": null
      },
      "start": 67,
      "end": 68,
      "loc": {
        "start": {
          "line": 2,
          "column": 29
        },
        "end": {
          "line": 2,
          "column": 30
        }
      }
    },
    {
      "type": {
        "label": "name",
        "beforeExpr": false,
        "startsExpr": true,
        "rightAssociative": false,
        "isLoop": false,
        "isAssign": false,
        "prefix": false,
        "postfix": false,
        "binop": null
      },
      "value": "from",
      "start": 69,
      "end": 73,
      "loc": {
        "start": {
          "line": 2,
          "column": 31
        },
        "end": {
          "line": 2,
          "column": 35
        }
      }
    },
    {
      "type": {
        "label": "string",
        "beforeExpr": false,
        "startsExpr": true,
        "rightAssociative": false,
        "isLoop": false,
        "isAssign": false,
        "prefix": false,
        "postfix": false,
        "binop": null,
        "updateContext": null
      },
      "value": "../actions/OrderActions",
      "start": 74,
      "end": 99,
      "loc": {
        "start": {
          "line": 2,
          "column": 36
        },
        "end": {
          "line": 2,
          "column": 61
        }
      }
    },
    {
      "type": {
        "label": "import",
        "keyword": "import",
        "beforeExpr": false,
        "startsExpr": false,
        "rightAssociative": false,
        "isLoop": false,
        "isAssign": false,
        "prefix": false,
        "postfix": false,
        "binop": null,
        "updateContext": null
      },
      "value": "import",
      "start": 100,
      "end": 106,
      "loc": {
        "start": {
          "line": 3,
          "column": 0
        },
        "end": {
          "line": 3,
          "column": 6
        }
      }
    },
    {
      "type": {
        "label": "{",
        "beforeExpr": true,
        "startsExpr": true,
        "rightAssociative": false,
        "isLoop": false,
        "isAssign": false,
        "prefix": false,
        "postfix": false,
        "binop": null
      },
      "start": 107,
      "end": 108,
      "loc": {
        "start": {
          "line": 3,
          "column": 7
        },
        "end": {
          "line": 3,
          "column": 8
        }
      }
    },
    {
      "type": {
        "label": "name",
        "beforeExpr": false,
        "startsExpr": true,
        "rightAssociative": false,
        "isLoop": false,
        "isAssign": false,
        "prefix": false,
        "postfix": false,
        "binop": null
      },
      "value": "uiHideMenu",
      "start": 109,
      "end": 119,
      "loc": {
        "start": {
          "line": 3,
          "column": 9
        },
        "end": {
          "line": 3,
          "column": 19
        }
      }
    },
    {
      "type": {
        "label": "}",
        "beforeExpr": false,
        "startsExpr": false,
        "rightAssociative": false,
        "isLoop": false,
        "isAssign": false,
        "prefix": false,
        "postfix": false,
        "binop": null
      },
      "start": 120,
      "end": 121,
      "loc": {
        "start": {
          "line": 3,
          "column": 20
        },
        "end": {
          "line": 3,
          "column": 21
        }
      }
    },
    {
      "type": {
        "label": "name",
        "beforeExpr": false,
        "startsExpr": true,
        "rightAssociative": false,
        "isLoop": false,
        "isAssign": false,
        "prefix": false,
        "postfix": false,
        "binop": null
      },
      "value": "from",
      "start": 122,
      "end": 126,
      "loc": {
        "start": {
          "line": 3,
          "column": 22
        },
        "end": {
          "line": 3,
          "column": 26
        }
      }
    },
    {
      "type": {
        "label": "string",
        "beforeExpr": false,
        "startsExpr": true,
        "rightAssociative": false,
        "isLoop": false,
        "isAssign": false,
        "prefix": false,
        "postfix": false,
        "binop": null,
        "updateContext": null
      },
      "value": "../actions/UIActions",
      "start": 127,
      "end": 149,
      "loc": {
        "start": {
          "line": 3,
          "column": 27
        },
        "end": {
          "line": 3,
          "column": 49
        }
      }
    },
    {
      "type": {
        "label": "import",
        "keyword": "import",
        "beforeExpr": false,
        "startsExpr": false,
        "rightAssociative": false,
        "isLoop": false,
        "isAssign": false,
        "prefix": false,
        "postfix": false,
        "binop": null,
        "updateContext": null
      },
      "value": "import",
      "start": 150,
      "end": 156,
      "loc": {
        "start": {
          "line": 4,
          "column": 0
        },
        "end": {
          "line": 4,
          "column": 6
        }
      }
    },
    {
      "type": {
        "label": "name",
        "beforeExpr": false,
        "startsExpr": true,
        "rightAssociative": false,
        "isLoop": false,
        "isAssign": false,
        "prefix": false,
        "postfix": false,
        "binop": null
      },
      "value": "ModeSwitcher",
      "start": 157,
      "end": 169,
      "loc": {
        "start": {
          "line": 4,
          "column": 7
        },
        "end": {
          "line": 4,
          "column": 19
        }
      }
    },
    {
      "type": {
        "label": "name",
        "beforeExpr": false,
        "startsExpr": true,
        "rightAssociative": false,
        "isLoop": false,
        "isAssign": false,
        "prefix": false,
        "postfix": false,
        "binop": null
      },
      "value": "from",
      "start": 170,
      "end": 174,
      "loc": {
        "start": {
          "line": 4,
          "column": 20
        },
        "end": {
          "line": 4,
          "column": 24
        }
      }
    },
    {
      "type": {
        "label": "string",
        "beforeExpr": false,
        "startsExpr": true,
        "rightAssociative": false,
        "isLoop": false,
        "isAssign": false,
        "prefix": false,
        "postfix": false,
        "binop": null,
        "updateContext": null
      },
      "value": "../components/ModeSwitcher.jsx",
      "start": 175,
      "end": 207,
      "loc": {
        "start": {
          "line": 4,
          "column": 25
        },
        "end": {
          "line": 4,
          "column": 57
        }
      }
    },
    {
      "type": {
        "label": "const",
        "keyword": "const",
        "beforeExpr": false,
        "startsExpr": false,
        "rightAssociative": false,
        "isLoop": false,
        "isAssign": false,
        "prefix": false,
        "postfix": false,
        "binop": null,
        "updateContext": null
      },
      "value": "const",
      "start": 209,
      "end": 214,
      "loc": {
        "start": {
          "line": 6,
          "column": 0
        },
        "end": {
          "line": 6,
          "column": 5
        }
      }
    },
    {
      "type": {
        "label": "name",
        "beforeExpr": false,
        "startsExpr": true,
        "rightAssociative": false,
        "isLoop": false,
        "isAssign": false,
        "prefix": false,
        "postfix": false,
        "binop": null
      },
      "value": "mapStateToProps",
      "start": 215,
      "end": 230,
      "loc": {
        "start": {
          "line": 6,
          "column": 6
        },
        "end": {
          "line": 6,
          "column": 21
        }
      }
    },
    {
      "type": {
        "label": "=",
        "beforeExpr": true,
        "startsExpr": false,
        "rightAssociative": false,
        "isLoop": false,
        "isAssign": true,
        "prefix": false,
        "postfix": false,
        "binop": null,
        "updateContext": null
      },
      "value": "=",
      "start": 231,
      "end": 232,
      "loc": {
        "start": {
          "line": 6,
          "column": 22
        },
        "end": {
          "line": 6,
          "column": 23
        }
      }
    },
    {
      "type": {
        "label": "name",
        "beforeExpr": false,
        "startsExpr": true,
        "rightAssociative": false,
        "isLoop": false,
        "isAssign": false,
        "prefix": false,
        "postfix": false,
        "binop": null
      },
      "value": "state",
      "start": 233,
      "end": 238,
      "loc": {
        "start": {
          "line": 6,
          "column": 24
        },
        "end": {
          "line": 6,
          "column": 29
        }
      }
    },
    {
      "type": {
        "label": "=>",
        "beforeExpr": true,
        "startsExpr": false,
        "rightAssociative": false,
        "isLoop": false,
        "isAssign": false,
        "prefix": false,
        "postfix": false,
        "binop": null,
        "updateContext": null
      },
      "start": 239,
      "end": 241,
      "loc": {
        "start": {
          "line": 6,
          "column": 30
        },
        "end": {
          "line": 6,
          "column": 32
        }
      }
    },
    {
      "type": {
        "label": "{",
        "beforeExpr": true,
        "startsExpr": true,
        "rightAssociative": false,
        "isLoop": false,
        "isAssign": false,
        "prefix": false,
        "postfix": false,
        "binop": null
      },
      "start": 242,
      "end": 243,
      "loc": {
        "start": {
          "line": 6,
          "column": 33
        },
        "end": {
          "line": 6,
          "column": 34
        }
      }
    },
    {
      "type": {
        "label": "return",
        "keyword": "return",
        "beforeExpr": true,
        "startsExpr": false,
        "rightAssociative": false,
        "isLoop": false,
        "isAssign": false,
        "prefix": false,
        "postfix": false,
        "binop": null,
        "updateContext": null
      },
      "value": "return",
      "start": 246,
      "end": 252,
      "loc": {
        "start": {
          "line": 7,
          "column": 2
        },
        "end": {
          "line": 7,
          "column": 8
        }
      }
    },
    {
      "type": {
        "label": "{",
        "beforeExpr": true,
        "startsExpr": true,
        "rightAssociative": false,
        "isLoop": false,
        "isAssign": false,
        "prefix": false,
        "postfix": false,
        "binop": null
      },
      "start": 253,
      "end": 254,
      "loc": {
        "start": {
          "line": 7,
          "column": 9
        },
        "end": {
          "line": 7,
          "column": 10
        }
      }
    },
    {
      "type": {
        "label": "}",
        "beforeExpr": false,
        "startsExpr": false,
        "rightAssociative": false,
        "isLoop": false,
        "isAssign": false,
        "prefix": false,
        "postfix": false,
        "binop": null
      },
      "start": 254,
      "end": 255,
      "loc": {
        "start": {
          "line": 7,
          "column": 10
        },
        "end": {
          "line": 7,
          "column": 11
        }
      }
    },
    {
      "type": {
        "label": "}",
        "beforeExpr": false,
        "startsExpr": false,
        "rightAssociative": false,
        "isLoop": false,
        "isAssign": false,
        "prefix": false,
        "postfix": false,
        "binop": null
      },
      "start": 256,
      "end": 257,
      "loc": {
        "start": {
          "line": 8,
          "column": 0
        },
        "end": {
          "line": 8,
          "column": 1
        }
      }
    },
    {
      "type": {
        "label": "const",
        "keyword": "const",
        "beforeExpr": false,
        "startsExpr": false,
        "rightAssociative": false,
        "isLoop": false,
        "isAssign": false,
        "prefix": false,
        "postfix": false,
        "binop": null,
        "updateContext": null
      },
      "value": "const",
      "start": 259,
      "end": 264,
      "loc": {
        "start": {
          "line": 10,
          "column": 0
        },
        "end": {
          "line": 10,
          "column": 5
        }
      }
    },
    {
      "type": {
        "label": "name",
        "beforeExpr": false,
        "startsExpr": true,
        "rightAssociative": false,
        "isLoop": false,
        "isAssign": false,
        "prefix": false,
        "postfix": false,
        "binop": null
      },
      "value": "mapDispatchToProps",
      "start": 265,
      "end": 283,
      "loc": {
        "start": {
          "line": 10,
          "column": 6
        },
        "end": {
          "line": 10,
          "column": 24
        }
      }
    },
    {
      "type": {
        "label": "=",
        "beforeExpr": true,
        "startsExpr": false,
        "rightAssociative": false,
        "isLoop": false,
        "isAssign": true,
        "prefix": false,
        "postfix": false,
        "binop": null,
        "updateContext": null
      },
      "value": "=",
      "start": 284,
      "end": 285,
      "loc": {
        "start": {
          "line": 10,
          "column": 25
        },
        "end": {
          "line": 10,
          "column": 26
        }
      }
    },
    {
      "type": {
        "label": "name",
        "beforeExpr": false,
        "startsExpr": true,
        "rightAssociative": false,
        "isLoop": false,
        "isAssign": false,
        "prefix": false,
        "postfix": false,
        "binop": null
      },
      "value": "dispatch",
      "start": 286,
      "end": 294,
      "loc": {
        "start": {
          "line": 10,
          "column": 27
        },
        "end": {
          "line": 10,
          "column": 35
        }
      }
    },
    {
      "type": {
        "label": "=>",
        "beforeExpr": true,
        "startsExpr": false,
        "rightAssociative": false,
        "isLoop": false,
        "isAssign": false,
        "prefix": false,
        "postfix": false,
        "binop": null,
        "updateContext": null
      },
      "start": 295,
      "end": 297,
      "loc": {
        "start": {
          "line": 10,
          "column": 36
        },
        "end": {
          "line": 10,
          "column": 38
        }
      }
    },
    {
      "type": {
        "label": "{",
        "beforeExpr": true,
        "startsExpr": true,
        "rightAssociative": false,
        "isLoop": false,
        "isAssign": false,
        "prefix": false,
        "postfix": false,
        "binop": null
      },
      "start": 298,
      "end": 299,
      "loc": {
        "start": {
          "line": 10,
          "column": 39
        },
        "end": {
          "line": 10,
          "column": 40
        }
      }
    },
    {
      "type": {
        "label": "return",
        "keyword": "return",
        "beforeExpr": true,
        "startsExpr": false,
        "rightAssociative": false,
        "isLoop": false,
        "isAssign": false,
        "prefix": false,
        "postfix": false,
        "binop": null,
        "updateContext": null
      },
      "value": "return",
      "start": 302,
      "end": 308,
      "loc": {
        "start": {
          "line": 11,
          "column": 2
        },
        "end": {
          "line": 11,
          "column": 8
        }
      }
    },
    {
      "type": {
        "label": "{",
        "beforeExpr": true,
        "startsExpr": true,
        "rightAssociative": false,
        "isLoop": false,
        "isAssign": false,
        "prefix": false,
        "postfix": false,
        "binop": null
      },
      "start": 309,
      "end": 310,
      "loc": {
        "start": {
          "line": 11,
          "column": 9
        },
        "end": {
          "line": 11,
          "column": 10
        }
      }
    },
    {
      "type": {
        "label": "name",
        "beforeExpr": false,
        "startsExpr": true,
        "rightAssociative": false,
        "isLoop": false,
        "isAssign": false,
        "prefix": false,
        "postfix": false,
        "binop": null
      },
      "value": "onSwitch",
      "start": 315,
      "end": 323,
      "loc": {
        "start": {
          "line": 12,
          "column": 4
        },
        "end": {
          "line": 12,
          "column": 12
        }
      }
    },
    {
      "type": {
        "label": ":",
        "beforeExpr": true,
        "startsExpr": false,
        "rightAssociative": false,
        "isLoop": false,
        "isAssign": false,
        "prefix": false,
        "postfix": false,
        "binop": null,
        "updateContext": null
      },
      "start": 323,
      "end": 324,
      "loc": {
        "start": {
          "line": 12,
          "column": 12
        },
        "end": {
          "line": 12,
          "column": 13
        }
      }
    },
    {
      "type": {
        "label": "name",
        "beforeExpr": false,
        "startsExpr": true,
        "rightAssociative": false,
        "isLoop": false,
        "isAssign": false,
        "prefix": false,
        "postfix": false,
        "binop": null
      },
      "value": "mode",
      "start": 325,
      "end": 329,
      "loc": {
        "start": {
          "line": 12,
          "column": 14
        },
        "end": {
          "line": 12,
          "column": 18
        }
      }
    },
    {
      "type": {
        "label": "=>",
        "beforeExpr": true,
        "startsExpr": false,
        "rightAssociative": false,
        "isLoop": false,
        "isAssign": false,
        "prefix": false,
        "postfix": false,
        "binop": null,
        "updateContext": null
      },
      "start": 330,
      "end": 332,
      "loc": {
        "start": {
          "line": 12,
          "column": 19
        },
        "end": {
          "line": 12,
          "column": 21
        }
      }
    },
    {
      "type": {
        "label": "{",
        "beforeExpr": true,
        "startsExpr": true,
        "rightAssociative": false,
        "isLoop": false,
        "isAssign": false,
        "prefix": false,
        "postfix": false,
        "binop": null
      },
      "start": 333,
      "end": 334,
      "loc": {
        "start": {
          "line": 12,
          "column": 22
        },
        "end": {
          "line": 12,
          "column": 23
        }
      }
    },
    {
      "type": {
        "label": "name",
        "beforeExpr": false,
        "startsExpr": true,
        "rightAssociative": false,
        "isLoop": false,
        "isAssign": false,
        "prefix": false,
        "postfix": false,
        "binop": null
      },
      "value": "dispatch",
      "start": 341,
      "end": 349,
      "loc": {
        "start": {
          "line": 13,
          "column": 6
        },
        "end": {
          "line": 13,
          "column": 14
        }
      }
    },
    {
      "type": {
        "label": "(",
        "beforeExpr": true,
        "startsExpr": true,
        "rightAssociative": false,
        "isLoop": false,
        "isAssign": false,
        "prefix": false,
        "postfix": false,
        "binop": null
      },
      "start": 349,
      "end": 350,
      "loc": {
        "start": {
          "line": 13,
          "column": 14
        },
        "end": {
          "line": 13,
          "column": 15
        }
      }
    },
    {
      "type": {
        "label": "name",
        "beforeExpr": false,
        "startsExpr": true,
        "rightAssociative": false,
        "isLoop": false,
        "isAssign": false,
        "prefix": false,
        "postfix": false,
        "binop": null
      },
      "value": "changeOperationMode",
      "start": 350,
      "end": 369,
      "loc": {
        "start": {
          "line": 13,
          "column": 15
        },
        "end": {
          "line": 13,
          "column": 34
        }
      }
    },
    {
      "type": {
        "label": "(",
        "beforeExpr": true,
        "startsExpr": true,
        "rightAssociative": false,
        "isLoop": false,
        "isAssign": false,
        "prefix": false,
        "postfix": false,
        "binop": null
      },
      "start": 369,
      "end": 370,
      "loc": {
        "start": {
          "line": 13,
          "column": 34
        },
        "end": {
          "line": 13,
          "column": 35
        }
      }
    },
    {
      "type": {
        "label": "name",
        "beforeExpr": false,
        "startsExpr": true,
        "rightAssociative": false,
        "isLoop": false,
        "isAssign": false,
        "prefix": false,
        "postfix": false,
        "binop": null
      },
      "value": "mode",
      "start": 370,
      "end": 374,
      "loc": {
        "start": {
          "line": 13,
          "column": 35
        },
        "end": {
          "line": 13,
          "column": 39
        }
      }
    },
    {
      "type": {
        "label": ")",
        "beforeExpr": false,
        "startsExpr": false,
        "rightAssociative": false,
        "isLoop": false,
        "isAssign": false,
        "prefix": false,
        "postfix": false,
        "binop": null
      },
      "start": 374,
      "end": 375,
      "loc": {
        "start": {
          "line": 13,
          "column": 39
        },
        "end": {
          "line": 13,
          "column": 40
        }
      }
    },
    {
      "type": {
        "label": ")",
        "beforeExpr": false,
        "startsExpr": false,
        "rightAssociative": false,
        "isLoop": false,
        "isAssign": false,
        "prefix": false,
        "postfix": false,
        "binop": null
      },
      "start": 375,
      "end": 376,
      "loc": {
        "start": {
          "line": 13,
          "column": 40
        },
        "end": {
          "line": 13,
          "column": 41
        }
      }
    },
    {
      "type": {
        "label": "name",
        "beforeExpr": false,
        "startsExpr": true,
        "rightAssociative": false,
        "isLoop": false,
        "isAssign": false,
        "prefix": false,
        "postfix": false,
        "binop": null
      },
      "value": "dispatch",
      "start": 383,
      "end": 391,
      "loc": {
        "start": {
          "line": 14,
          "column": 6
        },
        "end": {
          "line": 14,
          "column": 14
        }
      }
    },
    {
      "type": {
        "label": "(",
        "beforeExpr": true,
        "startsExpr": true,
        "rightAssociative": false,
        "isLoop": false,
        "isAssign": false,
        "prefix": false,
        "postfix": false,
        "binop": null
      },
      "start": 391,
      "end": 392,
      "loc": {
        "start": {
          "line": 14,
          "column": 14
        },
        "end": {
          "line": 14,
          "column": 15
        }
      }
    },
    {
      "type": {
        "label": "name",
        "beforeExpr": false,
        "startsExpr": true,
        "rightAssociative": false,
        "isLoop": false,
        "isAssign": false,
        "prefix": false,
        "postfix": false,
        "binop": null
      },
      "value": "uiHideMenu",
      "start": 392,
      "end": 402,
      "loc": {
        "start": {
          "line": 14,
          "column": 15
        },
        "end": {
          "line": 14,
          "column": 25
        }
      }
    },
    {
      "type": {
        "label": "(",
        "beforeExpr": true,
        "startsExpr": true,
        "rightAssociative": false,
        "isLoop": false,
        "isAssign": false,
        "prefix": false,
        "postfix": false,
        "binop": null
      },
      "start": 402,
      "end": 403,
      "loc": {
        "start": {
          "line": 14,
          "column": 25
        },
        "end": {
          "line": 14,
          "column": 26
        }
      }
    },
    {
      "type": {
        "label": ")",
        "beforeExpr": false,
        "startsExpr": false,
        "rightAssociative": false,
        "isLoop": false,
        "isAssign": false,
        "prefix": false,
        "postfix": false,
        "binop": null
      },
      "start": 403,
      "end": 404,
      "loc": {
        "start": {
          "line": 14,
          "column": 26
        },
        "end": {
          "line": 14,
          "column": 27
        }
      }
    },
    {
      "type": {
        "label": ")",
        "beforeExpr": false,
        "startsExpr": false,
        "rightAssociative": false,
        "isLoop": false,
        "isAssign": false,
        "prefix": false,
        "postfix": false,
        "binop": null
      },
      "start": 404,
      "end": 405,
      "loc": {
        "start": {
          "line": 14,
          "column": 27
        },
        "end": {
          "line": 14,
          "column": 28
        }
      }
    },
    {
      "type": {
        "label": "}",
        "beforeExpr": false,
        "startsExpr": false,
        "rightAssociative": false,
        "isLoop": false,
        "isAssign": false,
        "prefix": false,
        "postfix": false,
        "binop": null
      },
      "start": 410,
      "end": 411,
      "loc": {
        "start": {
          "line": 15,
          "column": 4
        },
        "end": {
          "line": 15,
          "column": 5
        }
      }
    },
    {
      "type": {
        "label": "}",
        "beforeExpr": false,
        "startsExpr": false,
        "rightAssociative": false,
        "isLoop": false,
        "isAssign": false,
        "prefix": false,
        "postfix": false,
        "binop": null
      },
      "start": 414,
      "end": 415,
      "loc": {
        "start": {
          "line": 16,
          "column": 2
        },
        "end": {
          "line": 16,
          "column": 3
        }
      }
    },
    {
      "type": {
        "label": "}",
        "beforeExpr": false,
        "startsExpr": false,
        "rightAssociative": false,
        "isLoop": false,
        "isAssign": false,
        "prefix": false,
        "postfix": false,
        "binop": null
      },
      "start": 416,
      "end": 417,
      "loc": {
        "start": {
          "line": 17,
          "column": 0
        },
        "end": {
          "line": 17,
          "column": 1
        }
      }
    },
    {
      "type": {
        "label": "const",
        "keyword": "const",
        "beforeExpr": false,
        "startsExpr": false,
        "rightAssociative": false,
        "isLoop": false,
        "isAssign": false,
        "prefix": false,
        "postfix": false,
        "binop": null,
        "updateContext": null
      },
      "value": "const",
      "start": 419,
      "end": 424,
      "loc": {
        "start": {
          "line": 19,
          "column": 0
        },
        "end": {
          "line": 19,
          "column": 5
        }
      }
    },
    {
      "type": {
        "label": "name",
        "beforeExpr": false,
        "startsExpr": true,
        "rightAssociative": false,
        "isLoop": false,
        "isAssign": false,
        "prefix": false,
        "postfix": false,
        "binop": null
      },
      "value": "ModeSwitcherContainer",
      "start": 425,
      "end": 446,
      "loc": {
        "start": {
          "line": 19,
          "column": 6
        },
        "end": {
          "line": 19,
          "column": 27
        }
      }
    },
    {
      "type": {
        "label": "=",
        "beforeExpr": true,
        "startsExpr": false,
        "rightAssociative": false,
        "isLoop": false,
        "isAssign": true,
        "prefix": false,
        "postfix": false,
        "binop": null,
        "updateContext": null
      },
      "value": "=",
      "start": 447,
      "end": 448,
      "loc": {
        "start": {
          "line": 19,
          "column": 28
        },
        "end": {
          "line": 19,
          "column": 29
        }
      }
    },
    {
      "type": {
        "label": "name",
        "beforeExpr": false,
        "startsExpr": true,
        "rightAssociative": false,
        "isLoop": false,
        "isAssign": false,
        "prefix": false,
        "postfix": false,
        "binop": null
      },
      "value": "connect",
      "start": 449,
      "end": 456,
      "loc": {
        "start": {
          "line": 19,
          "column": 30
        },
        "end": {
          "line": 19,
          "column": 37
        }
      }
    },
    {
      "type": {
        "label": "(",
        "beforeExpr": true,
        "startsExpr": true,
        "rightAssociative": false,
        "isLoop": false,
        "isAssign": false,
        "prefix": false,
        "postfix": false,
        "binop": null
      },
      "start": 456,
      "end": 457,
      "loc": {
        "start": {
          "line": 19,
          "column": 37
        },
        "end": {
          "line": 19,
          "column": 38
        }
      }
    },
    {
      "type": {
        "label": "name",
        "beforeExpr": false,
        "startsExpr": true,
        "rightAssociative": false,
        "isLoop": false,
        "isAssign": false,
        "prefix": false,
        "postfix": false,
        "binop": null
      },
      "value": "mapStateToProps",
      "start": 460,
      "end": 475,
      "loc": {
        "start": {
          "line": 20,
          "column": 2
        },
        "end": {
          "line": 20,
          "column": 17
        }
      }
    },
    {
      "type": {
        "label": ",",
        "beforeExpr": true,
        "startsExpr": false,
        "rightAssociative": false,
        "isLoop": false,
        "isAssign": false,
        "prefix": false,
        "postfix": false,
        "binop": null,
        "updateContext": null
      },
      "start": 475,
      "end": 476,
      "loc": {
        "start": {
          "line": 20,
          "column": 17
        },
        "end": {
          "line": 20,
          "column": 18
        }
      }
    },
    {
      "type": {
        "label": "name",
        "beforeExpr": false,
        "startsExpr": true,
        "rightAssociative": false,
        "isLoop": false,
        "isAssign": false,
        "prefix": false,
        "postfix": false,
        "binop": null
      },
      "value": "mapDispatchToProps",
      "start": 479,
      "end": 497,
      "loc": {
        "start": {
          "line": 21,
          "column": 2
        },
        "end": {
          "line": 21,
          "column": 20
        }
      }
    },
    {
      "type": {
        "label": ")",
        "beforeExpr": false,
        "startsExpr": false,
        "rightAssociative": false,
        "isLoop": false,
        "isAssign": false,
        "prefix": false,
        "postfix": false,
        "binop": null
      },
      "start": 498,
      "end": 499,
      "loc": {
        "start": {
          "line": 22,
          "column": 0
        },
        "end": {
          "line": 22,
          "column": 1
        }
      }
    },
    {
      "type": {
        "label": "(",
        "beforeExpr": true,
        "startsExpr": true,
        "rightAssociative": false,
        "isLoop": false,
        "isAssign": false,
        "prefix": false,
        "postfix": false,
        "binop": null
      },
      "start": 499,
      "end": 500,
      "loc": {
        "start": {
          "line": 22,
          "column": 1
        },
        "end": {
          "line": 22,
          "column": 2
        }
      }
    },
    {
      "type": {
        "label": "name",
        "beforeExpr": false,
        "startsExpr": true,
        "rightAssociative": false,
        "isLoop": false,
        "isAssign": false,
        "prefix": false,
        "postfix": false,
        "binop": null
      },
      "value": "ModeSwitcher",
      "start": 500,
      "end": 512,
      "loc": {
        "start": {
          "line": 22,
          "column": 2
        },
        "end": {
          "line": 22,
          "column": 14
        }
      }
    },
    {
      "type": {
        "label": ")",
        "beforeExpr": false,
        "startsExpr": false,
        "rightAssociative": false,
        "isLoop": false,
        "isAssign": false,
        "prefix": false,
        "postfix": false,
        "binop": null
      },
      "start": 512,
      "end": 513,
      "loc": {
        "start": {
          "line": 22,
          "column": 14
        },
        "end": {
          "line": 22,
          "column": 15
        }
      }
    },
    {
      "type": {
        "label": "export",
        "keyword": "export",
        "beforeExpr": false,
        "startsExpr": false,
        "rightAssociative": false,
        "isLoop": false,
        "isAssign": false,
        "prefix": false,
        "postfix": false,
        "binop": null,
        "updateContext": null
      },
      "value": "export",
      "start": 515,
      "end": 521,
      "loc": {
        "start": {
          "line": 24,
          "column": 0
        },
        "end": {
          "line": 24,
          "column": 6
        }
      }
    },
    {
      "type": {
        "label": "default",
        "keyword": "default",
        "beforeExpr": true,
        "startsExpr": false,
        "rightAssociative": false,
        "isLoop": false,
        "isAssign": false,
        "prefix": false,
        "postfix": false,
        "binop": null,
        "updateContext": null
      },
      "value": "default",
      "start": 522,
      "end": 529,
      "loc": {
        "start": {
          "line": 24,
          "column": 7
        },
        "end": {
          "line": 24,
          "column": 14
        }
      }
    },
    {
      "type": {
        "label": "name",
        "beforeExpr": false,
        "startsExpr": true,
        "rightAssociative": false,
        "isLoop": false,
        "isAssign": false,
        "prefix": false,
        "postfix": false,
        "binop": null
      },
      "value": "ModeSwitcherContainer",
      "start": 530,
      "end": 551,
      "loc": {
        "start": {
          "line": 24,
          "column": 15
        },
        "end": {
          "line": 24,
          "column": 36
        }
      }
    },
    {
      "type": {
        "label": "eof",
        "beforeExpr": false,
        "startsExpr": false,
        "rightAssociative": false,
        "isLoop": false,
        "isAssign": false,
        "prefix": false,
        "postfix": false,
        "binop": null,
        "updateContext": null
      },
      "start": 552,
      "end": 552,
      "loc": {
        "start": {
          "line": 25,
          "column": 0
        },
        "end": {
          "line": 25,
          "column": 0
        }
      }
    }
  ]
}